CHANGES.txt
LICENSE.txt
MANIFEST.in
README.txt
setup.py
src/p01/__init__.py
src/p01.sampler.egg-info/PKG-INFO
src/p01.sampler.egg-info/SOURCES.txt
src/p01.sampler.egg-info/dependency_links.txt
src/p01.sampler.egg-info/namespace_packages.txt
src/p01.sampler.egg-info/not-zip-safe
src/p01.sampler.egg-info/requires.txt
src/p01.sampler.egg-info/top_level.txt
src/p01/sampler/README.txt
src/p01/sampler/__init__.py
src/p01/sampler/data.py
src/p01/sampler/interfaces.py
src/p01/sampler/manager.py
src/p01/sampler/meta.zcml
src/p01/sampler/plugin.py
src/p01/sampler/testlines.csv
src/p01/sampler/testlines.txt
src/p01/sampler/tests.py
src/p01/sampler/zcml.py