Metadata-Version: 1.0
Name: p01.sampler
Version: 0.5.0
Summary: Sampledata Generator
Home-page: http://pypi.python.org/pypi/p01.sampler
Author: Roger Ineichen and the Zope Community
Author-email: zope-dev@zope.org
License: ZPL 2.1
Keywords: zope3 p01 sample data generator
Platform: UNKNOWN
Classifier: Development Status :: 4 - Beta
Classifier: Environment :: Web Environment
Classifier: Intended Audience :: Developers
Classifier: License :: OSI Approved :: Zope Public License
Classifier: Programming Language :: Python
Classifier: Natural Language :: English
Classifier: Operating System :: OS Independent
Classifier: Topic :: Internet :: WWW/HTTP
Classifier: Framework :: Zope3
